GooBa/__init__.py
GooBa/gen.py
GooBa/Extern/JavaScript.py
GooBa/Extern/__init__.py
GooBa/Extern/project_generator.py
GooBa/Rendering/CSR.py
GooBa/Rendering/SSG.py
GooBa/Rendering/__init__.py
GooBa/component/Browser_Api.py
GooBa/component/Document.py
GooBa/component/Element.py
GooBa/component/HTMLElement.py
GooBa/component/Image.py
GooBa/component/Selectors.py
GooBa/component/__init__.py
GooBa/component/button.py
GooBa/component/component.py
GooBa/component/fetch.py
GooBa/component/form.py
GooBa/component/parent.py
GooBa/component/style.py
GooBa/hmr/__init__.py
GooBa/hmr/hmr.py
GooBa/router/__init__.py
GooBa/router/router.py
GooBa/router/router.test.py
GooBa-0.1.6.dist-info/LICENSE
GooBa-0.1.6.dist-info/METADATA
GooBa-0.1.6.dist-info/WHEEL
GooBa-0.1.6.dist-info/entry_points.txt
GooBa-0.1.6.dist-info/top_level.txt
GooBa-0.1.6.dist-info/RECORD
